{
  "station": {
    "id": "14480002",
    "label": "5 - 14480002 - BARCELOS",
    "name": "BARCELOS"
  },
  "source": "Histórico CSV + ANA HidroWebService",
  "generated_at": "2026-07-16T19:32:19-03:00",
  "status": "ok",
  "note": "Arquivo operacional com amostra recente. A base principal do projeto é diária.",
  "latest": {
    "datetime": "2026-07-16 19:00:00",
    "date": "2026-07-16",
    "level_cm": 912.0,
    "level_m": 9.12,
    "rain_mm": 0.0,
    "flow_m3s": null,
    "level_status": "0",
    "station_id": "14480002",
    "source": "api_ana"
  },
  "records": [
    {
      "datetime": "2026-07-16 00:15:00",
      "date": "2026-07-16",
      "level_cm": 914.55,
      "level_m": 9.146,
      "rain_mm": null,
      "flow_m3s": null,
      "level_status": "0",
      "station_id": "14480002",
      "source": "api_ana"
    },
    {
      "datetime": "2026-07-16 00:30:00",
      "date": "2026-07-16",
      "level_cm": 914.54,
      "level_m": 9.145,
      "rain_mm": null,
      "flow_m3s": null,
      "level_status": "0",
      "station_id": "14480002",
      "source": "api_ana"
    },
    {
      "datetime": "2026-07-16 00:45:00",
      "date": "2026-07-16",
      "level_cm": 914.52,
      "level_m": 9.145,
      "rain_mm": null,
      "flow_m3s": null,
      "level_status": "0",
      "station_id": "14480002",
      "source": "api_ana"
    },
    {
      "datetime": "2026-07-16 01:00:00",
      "date": "2026-07-16",
      "level_cm": 914.51,
      "level_m": 9.145,
      "rain_mm": null,
      "flow_m3s": null,
      "level_status": "0",
      "station_id": "14480002",
      "source": "api_ana"
    },
    {
      "datetime": "2026-07-16 01:15:00",
      "date": "2026-07-16",
      "level_cm": 914.49,
      "level_m": 9.145,
      "rain_mm": null,
      "flow_m3s": null,
      "level_status": "0",
      "station_id": "14480002",
      "source": "api_ana"
    },
    {
      "datetime": "2026-07-16 01:30:00",
      "date": "2026-07-16",
      "level_cm": 914.48,
      "level_m": 9.145,
      "rain_mm": null,
      "flow_m3s": null,
      "level_status": "0",
      "station_id": "14480002",
      "source": "api_ana"
    },
    {
      "datetime": "2026-07-16 01:45:00",
      "date": "2026-07-16",
      "level_cm": 914.46,
      "level_m": 9.145,
      "rain_mm": null,
      "flow_m3s": null,
      "level_status": "0",
      "station_id": "14480002",
      "source": "api_ana"
    },
    {
      "datetime": "2026-07-16 02:00:00",
      "date": "2026-07-16",
      "level_cm": 914.45,
      "level_m": 9.145,
      "rain_mm": null,
      "flow_m3s": null,
      "level_status": "0",
      "station_id": "14480002",
      "source": "api_ana"
    },
    {
      "datetime": "2026-07-16 02:15:00",
      "date": "2026-07-16",
      "level_cm": 914.43,
      "level_m": 9.144,
      "rain_mm": null,
      "flow_m3s": null,
      "level_status": "0",
      "station_id": "14480002",
      "source": "api_ana"
    },
    {
      "datetime": "2026-07-16 02:30:00",
      "date": "2026-07-16",
      "level_cm": 914.42,
      "level_m": 9.144,
      "rain_mm": null,
      "flow_m3s": null,
      "level_status": "0",
      "station_id": "14480002",
      "source": "api_ana"
    },
    {
      "datetime": "2026-07-16 02:45:00",
      "date": "2026-07-16",
      "level_cm": 914.4,
      "level_m": 9.144,
      "rain_mm": null,
      "flow_m3s": null,
      "level_status": "0",
      "station_id": "14480002",
      "source": "api_ana"
    },
    {
      "datetime": "2026-07-16 03:00:00",
      "date": "2026-07-16",
      "level_cm": 914.38,
      "level_m": 9.144,
      "rain_mm": null,
      "flow_m3s": null,
      "level_status": "0",
      "station_id": "14480002",
      "source": "api_ana"
    },
    {
      "datetime": "2026-07-16 03:15:00",
      "date": "2026-07-16",
      "level_cm": 914.37,
      "level_m": 9.144,
      "rain_mm": null,
      "flow_m3s": null,
      "level_status": "0",
      "station_id": "14480002",
      "source": "api_ana"
    },
    {
      "datetime": "2026-07-16 03:30:00",
      "date": "2026-07-16",
      "level_cm": 914.35,
      "level_m": 9.143,
      "rain_mm": null,
      "flow_m3s": null,
      "level_status": "0",
      "station_id": "14480002",
      "source": "api_ana"
    },
    {
      "datetime": "2026-07-16 03:45:00",
      "date": "2026-07-16",
      "level_cm": 914.34,
      "level_m": 9.143,
      "rain_mm": null,
      "flow_m3s": null,
      "level_status": "0",
      "station_id": "14480002",
      "source": "api_ana"
    },
    {
      "datetime": "2026-07-16 04:00:00",
      "date": "2026-07-16",
      "level_cm": 914.32,
      "level_m": 9.143,
      "rain_mm": null,
      "flow_m3s": null,
      "level_status": "0",
      "station_id": "14480002",
      "source": "api_ana"
    },
    {
      "datetime": "2026-07-16 04:15:00",
      "date": "2026-07-16",
      "level_cm": 914.31,
      "level_m": 9.143,
      "rain_mm": null,
      "flow_m3s": null,
      "level_status": "0",
      "station_id": "14480002",
      "source": "api_ana"
    },
    {
      "datetime": "2026-07-16 04:30:00",
      "date": "2026-07-16",
      "level_cm": 914.29,
      "level_m": 9.143,
      "rain_mm": null,
      "flow_m3s": null,
      "level_status": "0",
      "station_id": "14480002",
      "source": "api_ana"
    },
    {
      "datetime": "2026-07-16 04:45:00",
      "date": "2026-07-16",
      "level_cm": 914.28,
      "level_m": 9.143,
      "rain_mm": null,
      "flow_m3s": null,
      "level_status": "0",
      "station_id": "14480002",
      "source": "api_ana"
    },
    {
      "datetime": "2026-07-16 05:00:00",
      "date": "2026-07-16",
      "level_cm": 914.26,
      "level_m": 9.143,
      "rain_mm": null,
      "flow_m3s": null,
      "level_status": "0",
      "station_id": "14480002",
      "source": "api_ana"
    },
    {
      "datetime": "2026-07-16 05:15:00",
      "date": "2026-07-16",
      "level_cm": 914.25,
      "level_m": 9.143,
      "rain_mm": null,
      "flow_m3s": null,
      "level_status": "0",
      "station_id": "14480002",
      "source": "api_ana"
    },
    {
      "datetime": "2026-07-16 05:30:00",
      "date": "2026-07-16",
      "level_cm": 914.23,
      "level_m": 9.142,
      "rain_mm": null,
      "flow_m3s": null,
      "level_status": "0",
      "station_id": "14480002",
      "source": "api_ana"
    },
    {
      "datetime": "2026-07-16 05:45:00",
      "date": "2026-07-16",
      "level_cm": 914.22,
      "level_m": 9.142,
      "rain_mm": null,
      "flow_m3s": null,
      "level_status": "0",
      "station_id": "14480002",
      "source": "api_ana"
    },
    {
      "datetime": "2026-07-16 06:00:00",
      "date": "2026-07-16",
      "level_cm": 914.2,
      "level_m": 9.142,
      "rain_mm": null,
      "flow_m3s": null,
      "level_status": "0",
      "station_id": "14480002",
      "source": "api_ana"
    },
    {
      "datetime": "2026-07-16 06:15:00",
      "date": "2026-07-16",
      "level_cm": 914.18,
      "level_m": 9.142,
      "rain_mm": null,
      "flow_m3s": null,
      "level_status": "0",
      "station_id": "14480002",
      "source": "api_ana"
    },
    {
      "datetime": "2026-07-16 06:30:00",
      "date": "2026-07-16",
      "level_cm": 914.17,
      "level_m": 9.142,
      "rain_mm": null,
      "flow_m3s": null,
      "level_status": "0",
      "station_id": "14480002",
      "source": "api_ana"
    },
    {
      "datetime": "2026-07-16 06:45:00",
      "date": "2026-07-16",
      "level_cm": 914.15,
      "level_m": 9.142,
      "rain_mm": null,
      "flow_m3s": null,
      "level_status": "0",
      "station_id": "14480002",
      "source": "api_ana"
    },
    {
      "datetime": "2026-07-16 07:00:00",
      "date": "2026-07-16",
      "level_cm": 914.14,
      "level_m": 9.141,
      "rain_mm": null,
      "flow_m3s": null,
      "level_status": "0",
      "station_id": "14480002",
      "source": "api_ana"
    },
    {
      "datetime": "2026-07-16 07:15:00",
      "date": "2026-07-16",
      "level_cm": 914.12,
      "level_m": 9.141,
      "rain_mm": null,
      "flow_m3s": null,
      "level_status": "0",
      "station_id": "14480002",
      "source": "api_ana"
    },
    {
      "datetime": "2026-07-16 07:30:00",
      "date": "2026-07-16",
      "level_cm": 914.11,
      "level_m": 9.141,
      "rain_mm": null,
      "flow_m3s": null,
      "level_status": "0",
      "station_id": "14480002",
      "source": "api_ana"
    },
    {
      "datetime": "2026-07-16 07:45:00",
      "date": "2026-07-16",
      "level_cm": 914.09,
      "level_m": 9.141,
      "rain_mm": null,
      "flow_m3s": null,
      "level_status": "0",
      "station_id": "14480002",
      "source": "api_ana"
    },
    {
      "datetime": "2026-07-16 08:00:00",
      "date": "2026-07-16",
      "level_cm": 914.08,
      "level_m": 9.141,
      "rain_mm": null,
      "flow_m3s": null,
      "level_status": "0",
      "station_id": "14480002",
      "source": "api_ana"
    },
    {
      "datetime": "2026-07-16 08:15:00",
      "date": "2026-07-16",
      "level_cm": 914.06,
      "level_m": 9.141,
      "rain_mm": null,
      "flow_m3s": null,
      "level_status": "0",
      "station_id": "14480002",
      "source": "api_ana"
    },
    {
      "datetime": "2026-07-16 08:30:00",
      "date": "2026-07-16",
      "level_cm": 914.05,
      "level_m": 9.14,
      "rain_mm": null,
      "flow_m3s": null,
      "level_status": "0",
      "station_id": "14480002",
      "source": "api_ana"
    },
    {
      "datetime": "2026-07-16 08:45:00",
      "date": "2026-07-16",
      "level_cm": 914.03,
      "level_m": 9.14,
      "rain_mm": null,
      "flow_m3s": null,
      "level_status": "0",
      "station_id": "14480002",
      "source": "api_ana"
    },
    {
      "datetime": "2026-07-16 09:00:00",
      "date": "2026-07-16",
      "level_cm": 914.02,
      "level_m": 9.14,
      "rain_mm": null,
      "flow_m3s": null,
      "level_status": "0",
      "station_id": "14480002",
      "source": "api_ana"
    },
    {
      "datetime": "2026-07-16 09:15:00",
      "date": "2026-07-16",
      "level_cm": 914.0,
      "level_m": 9.14,
      "rain_mm": 12.2,
      "flow_m3s": null,
      "level_status": "0",
      "station_id": "14480002",
      "source": "api_ana"
    },
    {
      "datetime": "2026-07-16 09:30:00",
      "date": "2026-07-16",
      "level_cm": 914.0,
      "level_m": 9.14,
      "rain_mm": 0.0,
      "flow_m3s": null,
      "level_status": "0",
      "station_id": "14480002",
      "source": "api_ana"
    },
    {
      "datetime": "2026-07-16 09:45:00",
      "date": "2026-07-16",
      "level_cm": 914.0,
      "level_m": 9.14,
      "rain_mm": 0.0,
      "flow_m3s": null,
      "level_status": "0",
      "station_id": "14480002",
      "source": "api_ana"
    },
    {
      "datetime": "2026-07-16 10:00:00",
      "date": "2026-07-16",
      "level_cm": 914.0,
      "level_m": 9.14,
      "rain_mm": 0.2,
      "flow_m3s": null,
      "level_status": "0",
      "station_id": "14480002",
      "source": "api_ana"
    },
    {
      "datetime": "2026-07-16 10:15:00",
      "date": "2026-07-16",
      "level_cm": 914.0,
      "level_m": 9.14,
      "rain_mm": 0.4,
      "flow_m3s": null,
      "level_status": "0",
      "station_id": "14480002",
      "source": "api_ana"
    },
    {
      "datetime": "2026-07-16 10:30:00",
      "date": "2026-07-16",
      "level_cm": 914.0,
      "level_m": 9.14,
      "rain_mm": 0.2,
      "flow_m3s": null,
      "level_status": "0",
      "station_id": "14480002",
      "source": "api_ana"
    },
    {
      "datetime": "2026-07-16 10:45:00",
      "date": "2026-07-16",
      "level_cm": 913.0,
      "level_m": 9.13,
      "rain_mm": 0.2,
      "flow_m3s": null,
      "level_status": "0",
      "station_id": "14480002",
      "source": "api_ana"
    },
    {
      "datetime": "2026-07-16 11:00:00",
      "date": "2026-07-16",
      "level_cm": 914.0,
      "level_m": 9.14,
      "rain_mm": 0.0,
      "flow_m3s": null,
      "level_status": "0",
      "station_id": "14480002",
      "source": "api_ana"
    },
    {
      "datetime": "2026-07-16 11:15:00",
      "date": "2026-07-16",
      "level_cm": 913.0,
      "level_m": 9.13,
      "rain_mm": 0.0,
      "flow_m3s": null,
      "level_status": "0",
      "station_id": "14480002",
      "source": "api_ana"
    },
    {
      "datetime": "2026-07-16 11:30:00",
      "date": "2026-07-16",
      "level_cm": 913.0,
      "level_m": 9.13,
      "rain_mm": 0.0,
      "flow_m3s": null,
      "level_status": "0",
      "station_id": "14480002",
      "source": "api_ana"
    },
    {
      "datetime": "2026-07-16 11:45:00",
      "date": "2026-07-16",
      "level_cm": 913.0,
      "level_m": 9.13,
      "rain_mm": 0.0,
      "flow_m3s": null,
      "level_status": "0",
      "station_id": "14480002",
      "source": "api_ana"
    },
    {
      "datetime": "2026-07-16 12:00:00",
      "date": "2026-07-16",
      "level_cm": 913.0,
      "level_m": 9.13,
      "rain_mm": 0.0,
      "flow_m3s": null,
      "level_status": "0",
      "station_id": "14480002",
      "source": "api_ana"
    },
    {
      "datetime": "2026-07-16 12:15:00",
      "date": "2026-07-16",
      "level_cm": 913.0,
      "level_m": 9.13,
      "rain_mm": 0.0,
      "flow_m3s": null,
      "level_status": "0",
      "station_id": "14480002",
      "source": "api_ana"
    },
    {
      "datetime": "2026-07-16 12:30:00",
      "date": "2026-07-16",
      "level_cm": 913.0,
      "level_m": 9.13,
      "rain_mm": 0.0,
      "flow_m3s": null,
      "level_status": "0",
      "station_id": "14480002",
      "source": "api_ana"
    },
    {
      "datetime": "2026-07-16 12:45:00",
      "date": "2026-07-16",
      "level_cm": 913.0,
      "level_m": 9.13,
      "rain_mm": 0.0,
      "flow_m3s": null,
      "level_status": "0",
      "station_id": "14480002",
      "source": "api_ana"
    },
    {
      "datetime": "2026-07-16 13:00:00",
      "date": "2026-07-16",
      "level_cm": 913.0,
      "level_m": 9.13,
      "rain_mm": 0.0,
      "flow_m3s": null,
      "level_status": "0",
      "station_id": "14480002",
      "source": "api_ana"
    },
    {
      "datetime": "2026-07-16 13:15:00",
      "date": "2026-07-16",
      "level_cm": 913.0,
      "level_m": 9.13,
      "rain_mm": 0.0,
      "flow_m3s": null,
      "level_status": "0",
      "station_id": "14480002",
      "source": "api_ana"
    },
    {
      "datetime": "2026-07-16 13:30:00",
      "date": "2026-07-16",
      "level_cm": 913.0,
      "level_m": 9.13,
      "rain_mm": 0.0,
      "flow_m3s": null,
      "level_status": "0",
      "station_id": "14480002",
      "source": "api_ana"
    },
    {
      "datetime": "2026-07-16 13:45:00",
      "date": "2026-07-16",
      "level_cm": 913.0,
      "level_m": 9.13,
      "rain_mm": 0.0,
      "flow_m3s": null,
      "level_status": "0",
      "station_id": "14480002",
      "source": "api_ana"
    },
    {
      "datetime": "2026-07-16 14:00:00",
      "date": "2026-07-16",
      "level_cm": 913.0,
      "level_m": 9.13,
      "rain_mm": 0.0,
      "flow_m3s": null,
      "level_status": "0",
      "station_id": "14480002",
      "source": "api_ana"
    },
    {
      "datetime": "2026-07-16 14:15:00",
      "date": "2026-07-16",
      "level_cm": 913.0,
      "level_m": 9.13,
      "rain_mm": 0.0,
      "flow_m3s": null,
      "level_status": "0",
      "station_id": "14480002",
      "source": "api_ana"
    },
    {
      "datetime": "2026-07-16 14:30:00",
      "date": "2026-07-16",
      "level_cm": 913.0,
      "level_m": 9.13,
      "rain_mm": 0.0,
      "flow_m3s": null,
      "level_status": "0",
      "station_id": "14480002",
      "source": "api_ana"
    },
    {
      "datetime": "2026-07-16 14:45:00",
      "date": "2026-07-16",
      "level_cm": 913.0,
      "level_m": 9.13,
      "rain_mm": 0.0,
      "flow_m3s": null,
      "level_status": "0",
      "station_id": "14480002",
      "source": "api_ana"
    },
    {
      "datetime": "2026-07-16 15:00:00",
      "date": "2026-07-16",
      "level_cm": 913.0,
      "level_m": 9.13,
      "rain_mm": 0.0,
      "flow_m3s": null,
      "level_status": "0",
      "station_id": "14480002",
      "source": "api_ana"
    },
    {
      "datetime": "2026-07-16 15:15:00",
      "date": "2026-07-16",
      "level_cm": 913.0,
      "level_m": 9.13,
      "rain_mm": 0.0,
      "flow_m3s": null,
      "level_status": "0",
      "station_id": "14480002",
      "source": "api_ana"
    },
    {
      "datetime": "2026-07-16 15:30:00",
      "date": "2026-07-16",
      "level_cm": 912.0,
      "level_m": 9.12,
      "rain_mm": 0.0,
      "flow_m3s": null,
      "level_status": "0",
      "station_id": "14480002",
      "source": "api_ana"
    },
    {
      "datetime": "2026-07-16 15:45:00",
      "date": "2026-07-16",
      "level_cm": 912.0,
      "level_m": 9.12,
      "rain_mm": 0.0,
      "flow_m3s": null,
      "level_status": "0",
      "station_id": "14480002",
      "source": "api_ana"
    },
    {
      "datetime": "2026-07-16 16:00:00",
      "date": "2026-07-16",
      "level_cm": 912.0,
      "level_m": 9.12,
      "rain_mm": 0.0,
      "flow_m3s": null,
      "level_status": "0",
      "station_id": "14480002",
      "source": "api_ana"
    },
    {
      "datetime": "2026-07-16 16:15:00",
      "date": "2026-07-16",
      "level_cm": 912.0,
      "level_m": 9.12,
      "rain_mm": 0.0,
      "flow_m3s": null,
      "level_status": "0",
      "station_id": "14480002",
      "source": "api_ana"
    },
    {
      "datetime": "2026-07-16 16:30:00",
      "date": "2026-07-16",
      "level_cm": 912.0,
      "level_m": 9.12,
      "rain_mm": 0.0,
      "flow_m3s": null,
      "level_status": "0",
      "station_id": "14480002",
      "source": "api_ana"
    },
    {
      "datetime": "2026-07-16 16:45:00",
      "date": "2026-07-16",
      "level_cm": 912.0,
      "level_m": 9.12,
      "rain_mm": 0.0,
      "flow_m3s": null,
      "level_status": "0",
      "station_id": "14480002",
      "source": "api_ana"
    },
    {
      "datetime": "2026-07-16 17:00:00",
      "date": "2026-07-16",
      "level_cm": 912.0,
      "level_m": 9.12,
      "rain_mm": 0.0,
      "flow_m3s": null,
      "level_status": "0",
      "station_id": "14480002",
      "source": "api_ana"
    },
    {
      "datetime": "2026-07-16 17:15:00",
      "date": "2026-07-16",
      "level_cm": 912.0,
      "level_m": 9.12,
      "rain_mm": 0.0,
      "flow_m3s": null,
      "level_status": "0",
      "station_id": "14480002",
      "source": "api_ana"
    },
    {
      "datetime": "2026-07-16 17:30:00",
      "date": "2026-07-16",
      "level_cm": 912.0,
      "level_m": 9.12,
      "rain_mm": 0.0,
      "flow_m3s": null,
      "level_status": "0",
      "station_id": "14480002",
      "source": "api_ana"
    },
    {
      "datetime": "2026-07-16 17:45:00",
      "date": "2026-07-16",
      "level_cm": 912.0,
      "level_m": 9.12,
      "rain_mm": 0.0,
      "flow_m3s": null,
      "level_status": "0",
      "station_id": "14480002",
      "source": "api_ana"
    },
    {
      "datetime": "2026-07-16 18:00:00",
      "date": "2026-07-16",
      "level_cm": 912.0,
      "level_m": 9.12,
      "rain_mm": 0.0,
      "flow_m3s": null,
      "level_status": "0",
      "station_id": "14480002",
      "source": "api_ana"
    },
    {
      "datetime": "2026-07-16 18:15:00",
      "date": "2026-07-16",
      "level_cm": 912.0,
      "level_m": 9.12,
      "rain_mm": 0.0,
      "flow_m3s": null,
      "level_status": "0",
      "station_id": "14480002",
      "source": "api_ana"
    },
    {
      "datetime": "2026-07-16 18:30:00",
      "date": "2026-07-16",
      "level_cm": 912.0,
      "level_m": 9.12,
      "rain_mm": 0.0,
      "flow_m3s": null,
      "level_status": "0",
      "station_id": "14480002",
      "source": "api_ana"
    },
    {
      "datetime": "2026-07-16 18:45:00",
      "date": "2026-07-16",
      "level_cm": 912.0,
      "level_m": 9.12,
      "rain_mm": 0.0,
      "flow_m3s": null,
      "level_status": "0",
      "station_id": "14480002",
      "source": "api_ana"
    },
    {
      "datetime": "2026-07-16 19:00:00",
      "date": "2026-07-16",
      "level_cm": 912.0,
      "level_m": 9.12,
      "rain_mm": 0.0,
      "flow_m3s": null,
      "level_status": "0",
      "station_id": "14480002",
      "source": "api_ana"
    }
  ]
}