{
  "station": {
    "id": "14480002",
    "label": "5 - 14480002 - BARCELOS",
    "name": "BARCELOS"
  },
  "source": "Histórico CSV + ANA HidroWebService",
  "generated_at": "2026-07-18T07:47:58-03:00",
  "status": "ok",
  "latest": {
    "date": "2026-07-18",
    "level_avg_m": 9.066,
    "level_min_m": 9.06,
    "level_max_m": 9.07,
    "level_first_m": 9.07,
    "level_last_m": 9.06,
    "level_avg_cm": 906.59,
    "samples": 29,
    "first_datetime": "2026-07-18 00:00:00",
    "last_datetime": "2026-07-18 07:00:00",
    "source": "api_ana"
  },
  "variation": {
    "last_24h_m": -0.01,
    "last_7d_m": -0.18,
    "trend": "estável",
    "trend_basis": "last_24h_m"
  }
}